{
  "id": "call_to_action",
  "type": "SharedSlice",
  "name": "CallToAction",
  "variations": [
    {
      "id": "default",
      "name": "Default",
      "description": "Default",
      "imageUrl": "https://images.prismic.io/foot-factor-uk/shared-slices/call_to_action/default/c59d61af897bd641f7a54c8acc0226575d221d40.png?auto=compress%2Cformat",
      "docURL": "...",
      "version": "initial",
      "primary": {
        "heading": {
          "type": "StructuredText",
          "config": {
            "label": "Heading",
            "placeholder": "",
            "multi": "strong,em,heading2,heading3,heading4,heading5,heading6",
            "allowTargetBlank": true
          }
        },
        "body": {
          "type": "StructuredText",
          "config": {
            "label": "Body",
            "placeholder": "",
            "multi": "paragraph,preformatted,heading1,heading2,heading3,heading4,heading5,heading6,strong,em,hyperlink,image,embed,list-item,o-list-item,rtl",
            "allowTargetBlank": true
          }
        },
        "links": {
          "type": "Link",
          "config": {
            "label": "Links",
            "placeholder": "",
            "select": null,
            "allowTargetBlank": true,
            "allowText": true,
            "repeat": true,
            "variants": [
              "Primary",
              "Secondary",
              "Outline"
            ]
          }
        },
        "image": {
          "type": "Image",
          "config": {
            "label": "Image",
            "constraint": {},
            "thumbnails": []
          }
        },
        "has_booking": {
          "type": "Boolean",
          "config": {
            "label": "Has Booking",
            "default_value": false,
            "placeholder_true": "true",
            "placeholder_false": "false"
          }
        },
        "booking_label": {
          "type": "Text",
          "config": {
            "label": "Booking Label",
            "placeholder": ""
          }
        }
      },
      "items": {}
    },
    {
      "id": "embedVideo",
      "name": "Embed Video",
      "description": "Default",
      "imageUrl": "https://images.prismic.io/slice-machine/621a5ec4-0387-4bc5-9860-2dd46cbc07cd_default_ss.png?auto=compress,format",
      "docURL": "...",
      "version": "initial",
      "primary": {
        "heading": {
          "type": "Text",
          "config": {
            "label": "Heading",
            "placeholder": ""
          }
        },
        "body": {
          "type": "StructuredText",
          "config": {
            "label": "Body",
            "placeholder": "",
            "multi": "paragraph,preformatted,heading1,heading2,heading3,heading4,heading5,heading6,strong,em,hyperlink,image,embed,list-item,o-list-item,rtl",
            "allowTargetBlank": true
          }
        },
        "links": {
          "type": "Link",
          "config": {
            "label": "Links",
            "placeholder": "",
            "select": null,
            "allowTargetBlank": true,
            "allowText": true,
            "repeat": true
          }
        },
        "class_name": {
          "type": "Text",
          "config": {
            "label": "Class Name",
            "placeholder": ""
          }
        },
        "video": {
          "type": "Embed",
          "config": {
            "label": "Video",
            "placeholder": ""
          }
        }
      },
      "items": {}
    },
    {
      "id": "ctaTwoColumns",
      "name": "cta-two-columns",
      "description": "Default",
      "imageUrl": "https://images.prismic.io/foot-factor-uk/shared-slices/call_to_action/ctaTwoColumns/61edffc41cddc28b29a6e76b464e8d60bceaecfc.png?auto=compress%2Cformat",
      "docURL": "...",
      "version": "initial",
      "primary": {
        "heading": {
          "type": "StructuredText",
          "config": {
            "label": "Heading",
            "placeholder": "",
            "multi": "strong,em,heading2,heading3,heading4,heading5,heading6",
            "allowTargetBlank": true
          }
        },
        "body": {
          "type": "StructuredText",
          "config": {
            "label": "Body",
            "placeholder": "",
            "multi": "paragraph,preformatted,heading1,heading2,heading3,heading4,heading5,heading6,strong,em,hyperlink,image,embed,list-item,o-list-item,rtl",
            "allowTargetBlank": true
          }
        },
        "links": {
          "type": "Link",
          "config": {
            "label": "Links",
            "placeholder": "",
            "select": null,
            "allowTargetBlank": true,
            "allowText": true,
            "repeat": true,
            "variants": [
              "Primary",
              "Secondary",
              "Outline"
            ]
          }
        },
        "image": {
          "type": "Image",
          "config": {
            "label": "Image",
            "constraint": {},
            "thumbnails": []
          }
        },
        "has_booking": {
          "type": "Boolean",
          "config": {
            "label": "Has Booking",
            "default_value": false,
            "placeholder_true": "true",
            "placeholder_false": "false"
          }
        },
        "booking_label": {
          "type": "Text",
          "config": {
            "label": "Booking Label",
            "placeholder": ""
          }
        }
      },
      "items": {}
    }
  ],
  "description": "CallToAction"
}